hyperdock_container/__init__.py
hyperdock_container/dock.py
hyperdock_container/runtime/__init__.py
hyperdock_container/runtime/runtime.py
hyperdock_container/runtime/docker/__init__.py
hyperdock_container/runtime/docker/runtime_docker.py
hyperdock_container/settings/__init__.py
hyperdock_container-0.5.7.dist-info/METADATA
hyperdock_container-0.5.7.dist-info/WHEEL
hyperdock_container-0.5.7.dist-info/top_level.txt
hyperdock_container-0.5.7.dist-info/RECORD
