Metadata-Version: 2.4
Name: hyperdock-container
Version: 0.5.7
Summary: Add your description here
Requires-Python: >=3.10
Requires-Dist: hyperpocket
Requires-Dist: pydantic>=2.10.2
Requires-Dist: docker>=7.1.0
